codeomatic/core/__init__.py
codeomatic/core/ratelimit.py
codeomatic-0.1.4.dist-info/LICENSE
codeomatic-0.1.4.dist-info/METADATA
codeomatic-0.1.4.dist-info/WHEEL
codeomatic-0.1.4.dist-info/top_level.txt
codeomatic-0.1.4.dist-info/RECORD
