Metadata-Version: 2.1
Name: codeomatic
Version: 0.1.4
Summary: A collection of common code for Codeomatic projects.
Home-page: https://github.com/codeomatic/core
Author: Denis Nikolskiy
Author-email: codeomatics@google.com
License: Apache 2.0
Platform: Posix; MacOS X; Windows
Classifier: Development Status :: 3 - Alpha
Classifier: Intended Audience :: Developers
Classifier: License :: OSI Approved :: Apache Software License
Classifier: Programming Language :: Python
Classifier: Programming Language :: Python :: 3
Classifier: Programming Language :: Python :: 3.5
Classifier: Programming Language :: Python :: 3.6
Classifier: Programming Language :: Python :: 3.7
Classifier: Operating System :: OS Independent
Classifier: Topic :: Internet
Requires-Python: >=3.5
